datasette_scribe/__init__.py
datasette_scribe/schema.sql
datasette_scribe/static/collection/index.min.css
datasette_scribe/static/collection/index.min.js
datasette_scribe/static/landing/index.min.css
datasette_scribe/static/landing/index.min.js
datasette_scribe/static/transcript/index.min.css
datasette_scribe/static/transcript/index.min.js
datasette_scribe/templates/collection.html
datasette_scribe/templates/landing.html
datasette_scribe/templates/transcript.html
datasette_scribe-0.1a5.dist-info/LICENSE
datasette_scribe-0.1a5.dist-info/METADATA
datasette_scribe-0.1a5.dist-info/WHEEL
datasette_scribe-0.1a5.dist-info/entry_points.txt
datasette_scribe-0.1a5.dist-info/top_level.txt
datasette_scribe-0.1a5.dist-info/RECORD
