Metadata-Version: 2.1
Name: datasette-scribe
Version: 0.1a5
Summary: Transcribe videos in Datasette
Author: Alex Garcia
License: Apache-2.0
Project-URL: Homepage, https://github.com/datasette/datasette-scribe
Project-URL: Changelog, https://github.com/datasette/datasette-scribe/releases
Project-URL: Issues, https://github.com/datasette/datasette-scribe/issues
Project-URL: CI, https://github.com/datasette/datasette-scribe/actions
Classifier: Framework :: Datasette
Classifier: License :: OSI Approved :: Apache Software License
Requires-Python: >=3.8
License-File: LICENSE
Requires-Dist: datasette
Requires-Dist: sqlite-utils
Requires-Dist: python-ulid
Provides-Extra: test
Requires-Dist: pytest ; extra == 'test'
Requires-Dist: pytest-asyncio ; extra == 'test'
Requires-Dist: pytest-httpx ; extra == 'test'
Requires-Dist: starlette ; extra == 'test'
